knob/__init__.py
knob/admin.py
knob/crypt.py
knob/db_router.py
knob/dt.py
knob/filters.py
knob/model.py
knob/paginations.py
knob/setting.py
knob/sync.py
knob/validators.py
knob/http/__init__.py
knob/http/request.py
knob/http/response.py
tests/__init__.py
tests/settings.py
tests/test_crypt.py
tests/test_dt.py
tests/test_setting.py
knob-0.0.43.dist-info/LICENSE
knob-0.0.43.dist-info/METADATA
knob-0.0.43.dist-info/WHEEL
knob-0.0.43.dist-info/top_level.txt
knob-0.0.43.dist-info/RECORD
