Metadata-Version: 2.1
Name: knob
Version: 0.0.43
Summary: Django utils collection
Home-page: https://github.com/claydodo/knob
Author: claydodo and his little friends (xiao huo ban)
Author-email: claydodo@foxmail.com
Classifier: Programming Language :: Python :: 2.7 
Classifier: Programming Language :: Python :: 3 
Classifier: Operating System :: OS Independent
License-File: LICENSE
Requires-Dist: six
Requires-Dist: pycryptodome
Requires-Dist: krux
Requires-Dist: krust
Requires-Dist: dt-utils
